[
    {
      "model": "products.product",
      "pk": 1,
      "fields": {
        "category": 1,
        "brand": 1,
        "name": "Gibson USA Les Paul Standard '50s Electric Guitar in Transparent Honey Amber",
        "description": "The iconic Gibson Les Paul Standard, a timeless classic that speaks for itself having been one the leading and most popular guitars in the music industry. The Gibson Les Paul Standard ‘50s Figured Top is a harkens back to the classic design and look that graced the stage 70 years ago. Featuring a solid Mahogany body, with AA figured Maple top in a Transparent Honey Amber Nitrocellulose finish, and PAF-style Pickups. This Les Paul utilises all the authentic era specifications that made you fall in love with this guitar in the first place. The Mahogany “50s Style” neck has a chunkier feel, compared to the slim taper of later Les Paul designs, giving you comfortable thumb support moving around the neck.",
        "price": "1999.99",
        "image": "products/superwidget30gibson-usa-les-paul-standard-50s-transparent-honey-amber.jpeg"
      }
    },
    {
      "model": "products.product",
      "pk": 2,
      "fields": {
        "category": 2,
        "brand": 3,
        "name": "MegaGadget Pro",
        "description": "High-end gadget for professional use.",
        "price": "499.50",
        "image": "products/megagadgetpro.jpg"
      }
    }
  ]